table_compositor/__init__.py
table_compositor/grid.py
table_compositor/html_styles.py
table_compositor/html_writer.py
table_compositor/presentation_model.py
table_compositor/table_compositor.py
table_compositor/util.py
table_compositor/xlsx_styles.py
table_compositor/xlsx_writer.py
table_compositor-1.1.4.dist-info/LICENSE
table_compositor-1.1.4.dist-info/METADATA
table_compositor-1.1.4.dist-info/WHEEL
table_compositor-1.1.4.dist-info/top_level.txt
table_compositor-1.1.4.dist-info/RECORD
