Metadata-Version: 2.1
Name: table-compositor
Version: 1.1.4
Summary: Library to render table-like data structure into XLSX and other formats.
Home-page: https://github.com/InvestmentSystems/table-compositor
Author: Guru Devanla
License: MIT
Keywords: pandas excel writer table
Platform: UNKNOWN
Classifier: Development Status :: 5 - Production/Stable
Classifier: Intended Audience :: Developers
Classifier: Topic :: Software Development
Classifier: License :: OSI Approved :: MIT License
Classifier: Programming Language :: Python :: 3.4
Classifier: Programming Language :: Python :: 3.5
License-File: LICENSE
Requires-Dist: pandas (==0.24.2)
Requires-Dist: numpy (>=1.17.4)
Requires-Dist: openpyxl (>=2.5.4)
Requires-Dist: xlsxwriter (>=1.1.2)
Requires-Dist: Pygments (>=2.7.4)
Requires-Dist: sphinx-jinja (>=1.1.1)
Requires-Dist: sphinxcontrib-napoleon (>=0.7)
Requires-Dist: sphinx-rtd-theme (>=0.5.0)
Requires-Dist: static-frame (>=0.8.14)
